ndk/appid_service_pb2.py
ndk/appid_service_pb2_grpc.py
ndk/bfd_service_pb2.py
ndk/bfd_service_pb2_grpc.py
ndk/config_service_pb2.py
ndk/config_service_pb2_grpc.py
ndk/interface_service_pb2.py
ndk/interface_service_pb2_grpc.py
ndk/lldp_service_pb2.py
ndk/lldp_service_pb2_grpc.py
ndk/networkinstance_service_pb2.py
ndk/networkinstance_service_pb2_grpc.py
ndk/nexthop_group_service_pb2.py
ndk/nexthop_group_service_pb2_grpc.py
ndk/route_service_pb2.py
ndk/route_service_pb2_grpc.py
ndk/sdk_common_pb2.py
ndk/sdk_common_pb2_grpc.py
ndk/sdk_service_pb2.py
ndk/sdk_service_pb2_grpc.py
ndk/telemetry_service_pb2.py
ndk/telemetry_service_pb2_grpc.py
srlinux_ndk-0.5.0.dist-info/LICENSE.md
srlinux_ndk-0.5.0.dist-info/METADATA
srlinux_ndk-0.5.0.dist-info/WHEEL
srlinux_ndk-0.5.0.dist-info/top_level.txt
srlinux_ndk-0.5.0.dist-info/RECORD
