Metadata-Version: 2.1
Name: srlinux-ndk
Version: 0.5.0
Summary: Nokia SR Linux NetOps Development Kit
Home-page: https://github.com/nokia/srlinux-ndk-py
Author: Nokia
Author-email: roman.dodin@nokia.com
License: UNKNOWN
Platform: UNKNOWN
Classifier: Topic :: Utilities
Classifier: Programming Language :: Python
Classifier: Programming Language :: Python :: 3
Classifier: Programming Language :: Python :: 3.6
Classifier: Programming Language :: Python :: 3.7
Classifier: Programming Language :: Python :: 3.8
Classifier: Operating System :: POSIX :: Linux
Classifier: Operating System :: MacOS
